kitcolors/__init__.py
kitcolors/color.py
kitcolors/py.typed
kitcolors-1.9.0.dist-info/METADATA
kitcolors-1.9.0.dist-info/WHEEL
kitcolors-1.9.0.dist-info/RECORD
